{
  "title": "Vibrating surgical instrument for liposuction and other body contouring applications",
  "abstract": "A vibrating hand held surgical instrument for loosening tissue of a patient for liposuction or body contouring procedures. The instrument includes a motor connected to a vibration actuator having an eccentric rotating mass and an end effector for engaging tissue operatively connected to the vibration actuator, wherein the motor rotates the eccentric mass to cause the end effector to vibrate to loosen tissue. A flexible shaft having first end and second ends dampen the vibration to the motor and to the operator handle.",
  "claims": "1. A vibrating hand held surgical instrument for loosening tissue of a patient comprising: a motor; a rotating drive shaft having a first end and a second end, the first end operatively connected to the motor; a vibration actuator including an eccentric rotating mass operatively connected to the drive shaft, the eccentric rotating mass remaining outside the patient, the eccentric rotating mass positioned in a proximal housing; and a cannula extending distally of the eccentric rotating mass, wherein the motor is configured to rotate the eccentric mass to cause the cannula to vibrate to loosen tissue, and the cannula is operatively connected to the vibration actuator and removable from the vibration actuator for interchangeability of the cannula, the cannula having a lumen extending therein; wherein the cannula has an angled proximal region within the proximal housing of the instrument, the angled proximal region extending at an angle to a longitudinal axis of the instrument, wherein the angled proximal region is distal of the motor, the lumen of the cannula extending through the angled proximal region and the proximal end of the cannula extending outside a side of the proximal housing to connect with an external fluid source.",
  "patent_id": "US12376874-20250805",
  "classifications": {
    "ipc": [],
    "cpc": [
      "A61B 17/32",
      "A61B 17/32002",
      "A61B 17/320068",
      "A61M 1/76",
      "A61M 1/84",
      "A61M 1/89",
      "A61N 7/02",
      "A61B 2017/00398",
      "A61B 2017/00792",
      "A61B 2017/320028",
      "A61B 2017/32007",
      "A61B 2017/320084",
      "A61B 2017/320088",
      "A61B 2018/0019",
      "A61B 2018/00464",
      "A61B 2217/005",
      "A61B 2217/007",
      "A61M 1/77",
      "A61N 2007/025"
    ],
    "all": [
      "A61B 17/32",
      "A61B 17/32002",
      "A61B 17/320068",
      "A61M 1/76",
      "A61M 1/84",
      "A61M 1/89",
      "A61N 7/02",
      "A61B 2017/00398",
      "A61B 2017/00792",
      "A61B 2017/320028",
      "A61B 2017/32007",
      "A61B 2017/320084",
      "A61B 2017/320088",
      "A61B 2018/0019",
      "A61B 2018/00464",
      "A61B 2217/005",
      "A61B 2217/007",
      "A61M 1/77",
      "A61N 2007/025"
    ],
    "source": "converted"
  }
}