{
  "title": "Agriculture ground work vehicle monitoring system",
  "abstract": "A work vehicle includes a satellite positioning apparatus, a monitoring camera, a vehicle wireless communicator and an automated travel controller. A monitoring terminal includes an operation interface to be operated by a monitoring person, a monitor capable of displaying a shot image of the monitoring camera and a terminal wireless communicator. A relay apparatus is configured or programmed to relay data communication between the vehicle wireless communicator and the terminal wireless communicator.",
  "claims": "1. An agricultural ground work vehicle monitoring system comprising: a work vehicle capable of automated travel, including: a satellite positioning apparatus; a monitoring camera; a vehicle wireless communicator to perform Wi-Fi communication, the vehicle wireless communicator including an antenna; and an automated travel controller; a monitoring terminal including: an operation interface to be operated by a monitoring person; a monitor capable of displaying a shot image of the monitoring camera; and a terminal wireless communicator to perform Wi-Fi communication, the terminal wireless communicator including an antenna; and a relay apparatus configured or programmed to relay Wi-Fi data communication between the vehicle wireless communicator and the terminal wireless communicator,",
  "patent_id": "US12376510-20250805",
  "classifications": {
    "ipc": [],
    "cpc": [
      "A01B 69/008",
      "G05D 1/0022",
      "G05D 1/0044",
      "G05D 1/0278",
      "H04B 7/15507",
      "H04W 4/40",
      "H04W 40/22",
      "H04W 88/04"
    ],
    "all": [
      "A01B 69/008",
      "G05D 1/0022",
      "G05D 1/0044",
      "G05D 1/0278",
      "H04B 7/15507",
      "H04W 4/40",
      "H04W 40/22",
      "H04W 88/04"
    ],
    "source": "converted"
  }
}