{
  "application_id": "WO2020061350",
  "application_id_fs": null,
  "title": "Computing device and folio mode-detection system",
  "abstract": "In one general aspect, a folio can include a dock configured to receive a computing device, a base portion including a passive mode-detection component, a hinge assembly, and a base panel including an active mode-detection component. The base panel can be hingedly coupled via the hinge assembly to the base portion. The base panel can include a processing component configured to determine a mode of the folio based on the passive mode-detection component being detected by the active mode-detection component.",
  "claims": "Claims CLAIMS  What is claimed is: 1. A folio, comprising: a dock configured to receive a computing device; a base portion including a passive mode-detection component; a hinge assembly; and a base panel including an active mode-detection component, the base panel being hingedly coupled via the hinge assembly to the base portion, the base panel including a processing component configured to determine a mode of the folio based on the passive mode-detection component being detected by the active mode-detection component. 2. The folio of claim 1, wherein the base panel includes a keyboard. 3. The folio of claim 1, wherein the processing component is configured to send a mode signal representing the mode to the computing device via the dock. 4. The folio of claim 1 , wherein, in an entertainment mode of the computing device and the folio, the base portion and the base panel are aligned along a first plane non parallel to a second plane along which a display of the computing device is aligned, wherein the processing component is configured to send a mode signal representing that the computing device and the folio are collectively in the entertainment mode when the computing device and the folio are collectively in the entertainment mode. 5. The folio of claim 1, wherein, in a tablet mode of the computing device and the folio, the base portion, the base panel, and a display of the computing device are aligned along the same plane, wherein the processing component is configured to send a mode signal representing that the computing device and the folio are collectively in the tablet mode when the computing device and the folio are collectively in the tablet mode. 6. The folio of claim 1, wherein the processing component is configured to determine that the folio and the computing device are collectively in a laptop mode when the passive mode-detection component is not detected by the active mode-detection component. 7. The folio of claim 6, wherein the processing component is configured to send a mode signal indicating that the computing device and the folio are collectively in the laptop mode. 8. The folio of claim 1, wherein the passive mode-detection component is a magnet. 9. The folio of claim 1, wherein the active mode-detection component is a magnetometer. 10. The folio of claim 1, wherein the folio includes a rotatable portion hingedly coupled to the base portion. 11. The folio of claim 1, wherein the dock is rotatably coupled to a fabric included in the hinge assembly. 12. The folio of claim 1, wherein the processing component is configured to determine a mode of the folio based on the passive mode-detection component being within a threshold distance of the active mode-detection component. 13. A system comprising: a computing device including a display; and a folio for the computing device, including: a base portion including a passive mode-detection component, and a base panel including an active mode-detection component and hingedly coupled to the base portion, the folio configured to determine that the system is in a mode based on the passive mode-detection component being detected by the active mode-detection component. 14. The system of claim 13, wherein the folio further includes: \n\n a dock, and a processing component configured to send a mode signal representing the mode to the computing device via the dock. 15. The system of claim 13, wherein, in an entertainment mode of the computing device and the folio, the base portion and the base panel are aligned along a first plane non parallel to a second plane along which the display of the computing device is aligned, wherein the the folio is configured to send a mode signal representing that the computing device and the folio are collectively in the entertainment mode when the computing device and the folio are collectively in the entertainment mode. 16. The system of claim 13, wherein, in a tablet mode of the computing device and the folio, the base portion, the base panel, and the display of the computing device are aligned along the same plane, wherein the folio is configured to send a mode signal representing that the computing device and the folio are collectively in the tablet mode when the computing device and the folio are collectively in the tablet mode. 17. The system of claim 13, wherein the folio is configured to determine that the folio and the computing device are collectively in a laptop mode when the passive mode- detection component is not detected by the active mode-detection component. 18. A method, comprising: rotating a base panel of a folio including an active mode-detection component toward a passive mode-detection component included in a base portion of the folio, the base panel being hingedly coupled to the base portion; detecting, using the active mode-detection component and the passive mode- detection component, that the passive mode-detection component is within a threshold distance of the active mode-detection component; and sending to a computing device coupled to the folio via a dock and in response to the detecting, a mode signal indicating that the base panel is in contact with the base portion. 19. The method of claim 18, wherein the sending is from a processing component. 20. The method of claim 18, wherein the mode signal is a first mode signal, the method, further comprising: rotating the base panel of the folio away from the base portion of the folio; determining that the active mode-detection component no longer detects the passive mode-detection component; and sending to a computing device coupled to the folio via a dock and in response to the active mode-detection component no longer detecting the passive mode-detection component, a second mode signal indicating that the base panel is not in contact with the base portion. 21. A computer program product containing instructions that, when executed by a processor, cause the processor to: detect, using an active mode-detection component included in a base panel of a folio and a passive mode-detection component included in a base portion of the folio, the base panel being hingedly coupled to the base portion, that the base panel is in contact with the base portion by determining that the passive mode-detection component is within a threshold distance of the active mode-detection component; and send, to a computing device coupled to the folio via a dock and in response to the detecting, a mode signal indicating that the base panel is in contact with the base portion.",
  "classifications": {
    "ipc": [
      "G06F 1/16"
    ],
    "cpc": [],
    "all": [
      "G06F 1/16"
    ],
    "source": "csv"
  }
}